yyAutoAiframework/__init__.py
yyAutoAiframework/agi_common/AGIExtraParam.py
yyAutoAiframework/agi_common/AGIResponse.py
yyAutoAiframework/agi_common/DialogManager.py
yyAutoAiframework/agi_common/DialogManagerFactory.py
yyAutoAiframework/agi_common/PromptObject.py
yyAutoAiframework/agi_common/__init__.py
yyAutoAiframework/client/ARKClient.py
yyAutoAiframework/client/BaseAIClient.py
yyAutoAiframework/client/DashscopeClient.py
yyAutoAiframework/client/DeepSeekClient.py
yyAutoAiframework/client/MoonshotClient.py
yyAutoAiframework/client/OpenAIBaseClient.py
yyAutoAiframework/client/OpenAIClient.py
yyAutoAiframework/client/QianFanClient.py
yyAutoAiframework/client/__init__.py
yyAutoAiframework/compents/RagBotComponent.py
yyAutoAiframework/compents/__init__.py
yyAutoAiframework/util/AGIUtil.py
yyAutoAiframework/util/FileExtractUtil.py
yyAutoAiframework/util/RagUtil.py
yyAutoAiframework/util/__init__.py
yyAutoAiframework/vector_db/BaseVectorDb.py
yyAutoAiframework/vector_db/ChromaVectorDb.py
yyAutoAiframework/vector_db/ESVectorDb.py
yyAutoAiframework/vector_db/__init__.py
yyautoaiframework-1.0.10.dist-info/METADATA
yyautoaiframework-1.0.10.dist-info/WHEEL
yyautoaiframework-1.0.10.dist-info/top_level.txt
yyautoaiframework-1.0.10.dist-info/RECORD
