Metadata-Version: 2.4
Name: yyAutoAiframework
Version: 1.0.10
Summary: Add your description here
Home-page: https://github.com/zhangxcYouyou/ai_framework
Author: zhangxianchao
Author-email: 342588666@qq.com
Requires-Python: >=3.10
Requires-Dist: elasticsearch7>=7.17.12
Requires-Dist: numpy>=1.26.4
Requires-Dist: openai>=1.3.5
Requires-Dist: pandas>=2.2.3
Requires-Dist: pdfplumber>=0.11.6
Requires-Dist: pydantic>=2.11.3
Requires-Dist: python-dotenv>=1.1.0
Requires-Dist: qianfan>=0.4.12.3
Requires-Dist: requests>=2.32.3
Requires-Dist: volcengine-python-sdk>=1.0.118
Requires-Dist: chromadb-client>=1.0.5
Requires-Dist: setuptools>=78.1.0
Dynamic: author
Dynamic: author-email
Dynamic: description-content-type
Dynamic: home-page
Dynamic: requires-python
